uniplatform.py
uniplatform-0.1.2.data/scripts/uniplatform.py
uniplatform-0.1.2.dist-info/LICENSE
uniplatform-0.1.2.dist-info/METADATA
uniplatform-0.1.2.dist-info/WHEEL
uniplatform-0.1.2.dist-info/top_level.txt
uniplatform-0.1.2.dist-info/RECORD
